src/__init__.py
src/execution.py
src/executor.py
src/factory.py
src/machine/__init__.py
src/machine/persistent_statemachine.py
src/machine/state_machine.py
src/repository/__init__.py
src/repository/models.py
src/repository/repository.py
src/repository/sqlalchemy_postgres.py
src/repository/types.py
src/states/__init__.py
src/states/base.py
src/states/choice_state.md
src/states/choice_state.py
src/states/fail_state.md
src/states/fail_state.py
src/states/json_path.py
src/states/parallel_state.md
src/states/parallel_state.py
src/states/pass_state.md
src/states/pass_state.py
src/states/succeed.py
src/states/succeed_state.md
src/states/task_state.md
src/states/task_state.py
src/states/wait_state.md
src/states/wait_state.py
src/validator.py
state_machine_amz_py-0.0.1.dist-info/METADATA
state_machine_amz_py-0.0.1.dist-info/WHEEL
state_machine_amz_py-0.0.1.dist-info/entry_points.txt
state_machine_amz_py-0.0.1.dist-info/RECORD
