Metadata-Version: 2.4
Name: state-machine-amz-py
Version: 0.0.1
Summary: A powerful, extensible Amazon States Language based FSM implementation for Python with PostgreSQL persistence
License: MIT
Keywords: state-machine,finite-state-machine,fsm,workflow,automation,amazon-states-language,step-functions,orchestration,persistence,postgresql
Author: Hussain Pithawala
Author-email: hussainpithawala@gmail.com
Requires-Python: >=3.9,<4.0
Classifier: Development Status :: 4 - Beta
Classifier: Intended Audience :: Developers
Classifier: License :: OSI Approved :: MIT License
Classifier: Operating System :: OS Independent
Classifier: Programming Language :: Python :: 3
Classifier: Programming Language :: Python :: 3.9
Classifier: Programming Language :: Python :: 3.10
Classifier: Programming Language :: Python :: 3.11
Classifier: Programming Language :: Python :: 3.12
Classifier: Programming Language :: Python :: 3.13
Classifier: Programming Language :: Python :: 3.14
Classifier: Topic :: Software Development :: Libraries :: Python Modules
Classifier: Topic :: System :: Distributed Computing
Classifier: Typing :: Typed
Requires-Dist: jsonpath-ng (>=1.7.0,<2.0.0)
Requires-Dist: psycopg2-binary (>=2.9.0,<3.0.0)
Requires-Dist: pydantic (>=2.0,<3.0)
Requires-Dist: pyyaml (>=6.0,<7.0)
Requires-Dist: ramda (>=0.7.6,<0.8.0)
Requires-Dist: sqlalchemy (>=2.0.0,<3.0.0)
Requires-Dist: types-pyyaml (>=6.0.12.20250915,<7.0.0.0)
Project-URL: Bug Tracker, https://github.com/hussainpithawala/state-machine-amz-py/issues
Project-URL: Changelog, https://github.com/hussainpithawala/state-machine-amz-py/blob/main/CHANGELOG.md
Project-URL: Documentation, https://github.com/hussainpithawala/state-machine-amz-py#readme
Project-URL: Homepage, https://github.com/hussainpithawala/state-machine-amz-py
Project-URL: Repository, https://github.com/hussainpithawala/state-machine-amz-py
